<stg><name>horn_schunck_32</name>


<trans_list>

<trans id="18" from="1" to="2">
<condition id="-1">
<or_exp><and_exp></and_exp></or_exp>
</condition>
</trans>

<trans id="19" from="2" to="3">
<condition id="-1">
<or_exp><and_exp><literal name="icmp_ln76" val="0"/>
</and_exp></or_exp>
</condition>
</trans>

<trans id="21" from="3" to="2">
<condition id="-1">
<or_exp><and_exp></and_exp></or_exp>
</condition>
</trans>
</trans_list>



<state_list>

<state id="1" st_id="1">

<operation id="4" st_id="1" stage="1" lat="1">
<core>NULL</core>
<MemPortIdVec></MemPortIdVec>
<condition id="-1">
<or_exp><and_exp></and_exp></or_exp>
</condition>

<Node id="16" bw="3" op_0_bw="32">
<![CDATA[
entry:0 %iter = alloca i32 1

]]></Node>
<StgValue><ssdm name="iter"/></StgValue>
</operation>

<operation id="5" st_id="1" stage="1" lat="1">
<core>NULL</core>
<MemPortIdVec></MemPortIdVec>
<condition id="-1">
<or_exp><and_exp></and_exp></or_exp>
</condition>

<Node id="17" bw="0" op_0_bw="3" op_1_bw="3">
<![CDATA[
entry:1 %store_ln76 = store i3 0, i3 %iter

]]></Node>
<StgValue><ssdm name="store_ln76"/></StgValue>
</operation>

<operation id="6" st_id="1" stage="1" lat="1">
<core>NULL</core>
<MemPortIdVec></MemPortIdVec>
<condition id="-1">
<or_exp><and_exp></and_exp></or_exp>
</condition>

<Node id="18" bw="0" op_0_bw="0">
<![CDATA[
entry:2 %br_ln76 = br void %VITIS_LOOP_78_4

]]></Node>
<StgValue><ssdm name="br_ln76"/></StgValue>
</operation>
</state>

<state id="2" st_id="2">

<operation id="7" st_id="2" stage="1" lat="1">
<core>NULL</core>
<MemPortIdVec></MemPortIdVec>
<condition id="-1">
<or_exp><and_exp></and_exp></or_exp>
</condition>

<Node id="20" bw="3" op_0_bw="3" op_1_bw="0">
<![CDATA[
VITIS_LOOP_78_4:0 %iter_3 = load i3 %iter

]]></Node>
<StgValue><ssdm name="iter_3"/></StgValue>
</operation>

<operation id="8" st_id="2" stage="1" lat="1">
<core>Cmp</core>
<MemPortIdVec></MemPortIdVec>
<condition id="-1">
<or_exp><and_exp></and_exp></or_exp>
</condition>

<Node id="21" bw="1" op_0_bw="3" op_1_bw="3">
<![CDATA[
VITIS_LOOP_78_4:1 %icmp_ln76 = icmp_eq  i3 %iter_3, i3 5

]]></Node>
<StgValue><ssdm name="icmp_ln76"/></StgValue>
</operation>

<operation id="9" st_id="2" stage="1" lat="1">
<core>Adder</core>
<MemPortIdVec></MemPortIdVec>
<condition id="-1">
<or_exp><and_exp></and_exp></or_exp>
</condition>

<Node id="22" bw="3" op_0_bw="3" op_1_bw="3">
<![CDATA[
VITIS_LOOP_78_4:2 %iter_4 = add i3 %iter_3, i3 1

]]></Node>
<StgValue><ssdm name="iter_4"/></StgValue>
</operation>

<operation id="10" st_id="2" stage="1" lat="1">
<core>NULL</core>
<MemPortIdVec></MemPortIdVec>
<condition id="-1">
<or_exp><and_exp></and_exp></or_exp>
</condition>

<Node id="23" bw="0" op_0_bw="1" op_1_bw="0" op_2_bw="0">
<![CDATA[
VITIS_LOOP_78_4:3 %br_ln76 = br i1 %icmp_ln76, void %VITIS_LOOP_78_4.split, void %for.end146

]]></Node>
<StgValue><ssdm name="br_ln76"/></StgValue>
</operation>

<operation id="11" st_id="2" stage="2" lat="2">
<core></core>
<MemPortIdVec></MemPortIdVec>
<condition id="-1">
<or_exp><and_exp><literal name="icmp_ln76" val="0"/>
</and_exp></or_exp>
</condition>

<Node id="27" bw="0" op_0_bw="0" op_1_bw="16" op_2_bw="16" op_3_bw="16" op_4_bw="16" op_5_bw="16" op_6_bw="16" op_7_bw="16" op_8_bw="16" op_9_bw="16" op_10_bw="16" op_11_bw="16" op_12_bw="16" op_13_bw="16" op_14_bw="16" op_15_bw="16">
<![CDATA[
VITIS_LOOP_78_4.split:2 %call_ln0 = call void @horn_schunck_32_Pipeline_VITIS_LOOP_78_4_VITIS_LOOP_80_5, i16 %p_ZZ12pyramidal_hsPA64_8ap_fixedILi16ELi6EL9ap_q_mode5EL9ap_o_mode3ELi0EES4_S4_S4_35, i16 %p_ZZ12pyramidal_hsPA64_8ap_fixedILi16ELi6EL9ap_q_mode5EL9ap_o_mode3ELi0EES4_S4_S4_23, i16 %p_ZZ12pyramidal_hsPA64_8ap_fixedILi16ELi6EL9ap_q_mode5EL9ap_o_mode3ELi0EES4_S4_S4_34, i16 %p_ZZ12pyramidal_hsPA64_8ap_fixedILi16ELi6EL9ap_q_mode5EL9ap_o_mode3ELi0EES4_S4_S4_33, i16 %p_ZZ12pyramidal_hsPA64_8ap_fixedILi16ELi6EL9ap_q_mode5EL9ap_o_mode3ELi0EES4_S4_S4_32, i16 %p_ZZ12pyramidal_hsPA64_8ap_fixedILi16ELi6EL9ap_q_mode5EL9ap_o_mode3ELi0EES4_S4_S4_31, i16 %p_ZZ12pyramidal_hsPA64_8ap_fixedILi16ELi6EL9ap_q_mode5EL9ap_o_mode3ELi0EES4_S4_S4_30, i16 %p_ZZ12pyramidal_hsPA64_8ap_fixedILi16ELi6EL9ap_q_mode5EL9ap_o_mode3ELi0EES4_S4_S4_22, i16 %p_ZZ12pyramidal_hsPA64_8ap_fixedILi16ELi6EL9ap_q_mode5EL9ap_o_mode3ELi0EES4_S4_S4_21, i16 %p_ZZ12pyramidal_hsPA64_8ap_fixedILi16ELi6EL9ap_q_mode5EL9ap_o_mode3ELi0EES4_S4_S4_20, i16 %p_ZZ12pyramidal_hsPA64_8ap_fixedILi16ELi6EL9ap_q_mode5EL9ap_o_mode3ELi0EES4_S4_S4_19, i16 %p_ZZ12pyramidal_hsPA64_8ap_fixedILi16ELi6EL9ap_q_mode5EL9ap_o_mode3ELi0EES4_S4_S4_18, i16 %Ix32, i16 %Iy32, i16 %It32

]]></Node>
<StgValue><ssdm name="call_ln0"/></StgValue>
</operation>

<operation id="12" st_id="2" stage="1" lat="1">
<core>NULL</core>
<MemPortIdVec></MemPortIdVec>
<condition id="-1">
<or_exp><and_exp><literal name="icmp_ln76" val="0"/>
</and_exp></or_exp>
</condition>

<Node id="28" bw="0" op_0_bw="3" op_1_bw="3" op_2_bw="0" op_3_bw="0">
<![CDATA[
VITIS_LOOP_78_4.split:3 %store_ln76 = store i3 %iter_4, i3 %iter

]]></Node>
<StgValue><ssdm name="store_ln76"/></StgValue>
</operation>

<operation id="13" st_id="2" stage="1" lat="1">
<core>NULL</core>
<MemPortIdVec></MemPortIdVec>
<condition id="-1">
<or_exp><and_exp><literal name="icmp_ln76" val="1"/>
</and_exp></or_exp>
</condition>

<Node id="31" bw="0">
<![CDATA[
for.end146:0 %ret_ln95 = ret

]]></Node>
<StgValue><ssdm name="ret_ln95"/></StgValue>
</operation>
</state>

<state id="3" st_id="3">

<operation id="14" st_id="3" stage="1" lat="1">
<core>NULL</core>
<MemPortIdVec></MemPortIdVec>
<condition id="-1">
<or_exp><and_exp></and_exp></or_exp>
</condition>

<Node id="25" bw="0" op_0_bw="0" op_1_bw="64" op_2_bw="64" op_3_bw="64">
<![CDATA[
VITIS_LOOP_78_4.split:0 %speclooptripcount_ln76 = speclooptripcount void @_ssdm_op_SpecLoopTripCount, i64 5, i64 5, i64 5

]]></Node>
<StgValue><ssdm name="speclooptripcount_ln76"/></StgValue>
</operation>

<operation id="15" st_id="3" stage="1" lat="1">
<core>NULL</core>
<MemPortIdVec></MemPortIdVec>
<condition id="-1">
<or_exp><and_exp></and_exp></or_exp>
</condition>

<Node id="26" bw="0" op_0_bw="0" op_1_bw="0">
<![CDATA[
VITIS_LOOP_78_4.split:1 %specloopname_ln76 = specloopname void @_ssdm_op_SpecLoopName, void @empty

]]></Node>
<StgValue><ssdm name="specloopname_ln76"/></StgValue>
</operation>

<operation id="16" st_id="3" stage="1" lat="2">
<core></core>
<MemPortIdVec></MemPortIdVec>
<condition id="-1">
<or_exp><and_exp></and_exp></or_exp>
</condition>

<Node id="27" bw="0" op_0_bw="0" op_1_bw="16" op_2_bw="16" op_3_bw="16" op_4_bw="16" op_5_bw="16" op_6_bw="16" op_7_bw="16" op_8_bw="16" op_9_bw="16" op_10_bw="16" op_11_bw="16" op_12_bw="16" op_13_bw="16" op_14_bw="16" op_15_bw="16">
<![CDATA[
VITIS_LOOP_78_4.split:2 %call_ln0 = call void @horn_schunck_32_Pipeline_VITIS_LOOP_78_4_VITIS_LOOP_80_5, i16 %p_ZZ12pyramidal_hsPA64_8ap_fixedILi16ELi6EL9ap_q_mode5EL9ap_o_mode3ELi0EES4_S4_S4_35, i16 %p_ZZ12pyramidal_hsPA64_8ap_fixedILi16ELi6EL9ap_q_mode5EL9ap_o_mode3ELi0EES4_S4_S4_23, i16 %p_ZZ12pyramidal_hsPA64_8ap_fixedILi16ELi6EL9ap_q_mode5EL9ap_o_mode3ELi0EES4_S4_S4_34, i16 %p_ZZ12pyramidal_hsPA64_8ap_fixedILi16ELi6EL9ap_q_mode5EL9ap_o_mode3ELi0EES4_S4_S4_33, i16 %p_ZZ12pyramidal_hsPA64_8ap_fixedILi16ELi6EL9ap_q_mode5EL9ap_o_mode3ELi0EES4_S4_S4_32, i16 %p_ZZ12pyramidal_hsPA64_8ap_fixedILi16ELi6EL9ap_q_mode5EL9ap_o_mode3ELi0EES4_S4_S4_31, i16 %p_ZZ12pyramidal_hsPA64_8ap_fixedILi16ELi6EL9ap_q_mode5EL9ap_o_mode3ELi0EES4_S4_S4_30, i16 %p_ZZ12pyramidal_hsPA64_8ap_fixedILi16ELi6EL9ap_q_mode5EL9ap_o_mode3ELi0EES4_S4_S4_22, i16 %p_ZZ12pyramidal_hsPA64_8ap_fixedILi16ELi6EL9ap_q_mode5EL9ap_o_mode3ELi0EES4_S4_S4_21, i16 %p_ZZ12pyramidal_hsPA64_8ap_fixedILi16ELi6EL9ap_q_mode5EL9ap_o_mode3ELi0EES4_S4_S4_20, i16 %p_ZZ12pyramidal_hsPA64_8ap_fixedILi16ELi6EL9ap_q_mode5EL9ap_o_mode3ELi0EES4_S4_S4_19, i16 %p_ZZ12pyramidal_hsPA64_8ap_fixedILi16ELi6EL9ap_q_mode5EL9ap_o_mode3ELi0EES4_S4_S4_18, i16 %Ix32, i16 %Iy32, i16 %It32

]]></Node>
<StgValue><ssdm name="call_ln0"/></StgValue>
</operation>

<operation id="17" st_id="3" stage="1" lat="1">
<core>NULL</core>
<MemPortIdVec></MemPortIdVec>
<condition id="-1">
<or_exp><and_exp></and_exp></or_exp>
</condition>

<Node id="29" bw="0" op_0_bw="0">
<![CDATA[
VITIS_LOOP_78_4.split:4 %br_ln76 = br void %VITIS_LOOP_78_4

]]></Node>
<StgValue><ssdm name="br_ln76"/></StgValue>
</operation>
</state>
</state_list>


<ports>
</ports>


<dataflows>
</dataflows>


</stg>
